{"cameraMode":{"drawMode":0,"name":"Shaded","section":"Shading Mode"},"sceneLighting":true,"audioPlay":false,"sceneViewState":{"showFog":true,"showMaterialUpdate":false,"showSkybox":true,"showFlares":true,"showImageEffects":true,"showParticleSystems":true},"in2DMode":false,"pivot":{"x":6.80795955657959,"y":-7.802234649658203,"z":36.555545806884769},"rotation":{"x":0.2701609134674072,"y":-0.6414551138877869,"z":0.2587372660636902,"w":0.6697805523872376},"size":18.070175170898439,"orthographic":false}